dtawslayertool/__init__.py
dtawslayertool/app.py
dtawslayertool/version.py
dt_awslayertool-1.0.0.dist-info/LICENSE
dt_awslayertool-1.0.0.dist-info/METADATA
dt_awslayertool-1.0.0.dist-info/WHEEL
dt_awslayertool-1.0.0.dist-info/entry_points.txt
dt_awslayertool-1.0.0.dist-info/top_level.txt
dt_awslayertool-1.0.0.dist-info/RECORD
