Metadata-Version: 2.1
Name: dt-awslayertool
Version: 1.0.0
Summary: dt-awslayertool is a script to download or clone AWS Lambda Layers or extensions.
Home-page: https://github.com/dynatrace-oss/dt-awslayerool/
Author: Dynatrace, Inc.
Author-email: opensource@dynatrace.com
License: Apache 2
Keywords: aws,lambda,layer,dynatrace,cli,oneagent
Platform: UNKNOWN
Classifier: Development Status :: 5 - Production/Stable
Classifier: Environment :: Console
Classifier: License :: OSI Approved
Classifier: License :: OSI Approved :: Apache Software License
Classifier: Programming Language :: Python :: 3
Classifier: Programming Language :: Python :: 3.6
Classifier: Programming Language :: Python :: 3.7
Classifier: Programming Language :: Python :: 3.8
Classifier: Programming Language :: Python :: 3.9
Classifier: Intended Audience :: Developers
Classifier: Intended Audience :: System Administrators
Classifier: Topic :: System :: Systems Administration
Classifier: Topic :: System :: Software Distribution
Classifier: Topic :: Utilities
Requires-Python: >=3.6
Requires-Dist: boto3 (~=1.17)
